pochta/__init__.py
pochta/__version__.py
pochta/delivery.py
pochta/enums.py
pochta/exceptions.py
pochta/helpers.py
pochta/tracking.py
pochta/utils.py
pochta/api/__init__.py
pochta/api/archive.py
pochta/api/batches.py
pochta/api/documents.py
pochta/api/lta.py
pochta/api/nogroup.py
pochta/api/orders.py
pochta/api/services.py
pochta/api/settings.py
fs_pochta_api-1.2.1.dist-info/LICENSE
fs_pochta_api-1.2.1.dist-info/METADATA
fs_pochta_api-1.2.1.dist-info/WHEEL
fs_pochta_api-1.2.1.dist-info/top_level.txt
fs_pochta_api-1.2.1.dist-info/RECORD
