Metadata-Version: 2.1
Name: fs-pochta-api
Version: 1.2.1
Summary: Библиотека для работы с API Почты России
Home-page: https://github.com/fogstream/fs-pochta-api
Maintainer: fadedDexofan
Maintainer-email: fadeddexofan@gmail.com
License: MIT
Keywords: pochta,api,wrapper,fs-pochta-api,sdk,integration,fogstream,lib
Platform: UNKNOWN
Classifier: License :: OSI Approved :: MIT License
Classifier: Development Status :: 5 - Production/Stable
Classifier: Intended Audience :: Developers
Classifier: Operating System :: Unix
Classifier: Topic :: Software Development :: Libraries
Classifier: Programming Language :: Python :: 3
Classifier: Programming Language :: Python :: 3.6
Classifier: Programming Language :: Python :: 3.7
Classifier: Programming Language :: Python :: 3.8
Classifier: Programming Language :: Python :: Implementation :: CPython
Requires-Python: >=3.6.0
Requires-Dist: requests
Requires-Dist: boltons
Requires-Dist: zeep
Provides-Extra: dev
Requires-Dist: isort ; extra == 'dev'
Requires-Dist: flake8 ; extra == 'dev'
Requires-Dist: pylint ; extra == 'dev'
